<?xml version="1.0" encoding="UTF-8"?>
<Rezept>
   <meta>
       <NaehrwertProPerson>717 kcal</NaehrwertProPerson>
       <Fett>40 g  </Fett>
       <Kohlenhydrate>79 g  </Kohlenhydrate>
       <Eiweiss>8 g   </Eiweiss>
   </meta>
   <einkaufliste>
      <Linzerteig>
          <quant>250 g</quant>
          <zutat>lactosefreie Butter, weich</zutat>
          <quant>200 g</quant>
          <zutat>Zucker</zutat>
          <quant>1 Prise</quant>
          <zutat>Salz</zutat>
          <quant>2 </quant>
          <zutat>Eier</zutat>
          <quant>1 </quant>
          <zutat>Bio-Zitrone, nur abgeriebene Schale</zutat>
          <quant>300 g</quant>
          <zutat>glutenfreies Mehl (Schaer)</zutat>
          <quant>200 g</quant>
          <zutat>gemahlene Mandeln</zutat>
          <quant>1/4 TL</quant>
          <zutat>Zimt</zutat>
          <quant>1 Msp.</quant>
          <zutat>Nelkenpulver</zutat>
      </Linzerteig>
      <Fuellung   >
          <quant>300 g</quant>
          <zutat>Himbeerkonfituere</zutat>
      </Fuellung   >
   </einkaufliste>
   <rezept>
      <How_To    >
          <inhalt>Linzerteig                    </inhalt>
      </How_To    >
      <Linzerteig>
          <inhalt>Butter in eine Schuessel geben, Zucker und Salz darunterruehren. Eier beigeben, weiterruehren, bis die Masse heller ist. Zitronenschale darunterruehren. Mehl, Mandeln, Zimt und Nelkenpulver mischen, unter die Masse mischen. 3/4 des Teiges in die 8 Foermchen verteilen, glatt streichen.</inhalt>
      </Linzerteig>
      <How_To1   >
          <inhalt>Konfituere glatt ruehren, auf den Teigboeden verteilen, dabei ringsum je einen Rand von ca. 2 cm frei lassen.</inhalt>
      </How_To1   >
      <Fuellung   >
          <inhalt>Backen: ca. 25 Min. in der unteren Haelfte des auf 180 Grad vorgeheizten Ofens. Herausnehmen, etwas abkuehlen, aus den Foermchen nehmen, auf einem Gitter auskuehlen.</inhalt>
      </Fuellung   >
   </rezept>
</Rezept>