<?xml version="1.0" encoding="UTF-8"?>
<Rezept>
   <meta>
       <NaehrwertProPerson>509 kcal</NaehrwertProPerson>
       <Fett>32 g  </Fett>
       <Kohlenhydrate>38 g  </Kohlenhydrate>
       <Eiweiss>14 g  </Eiweiss>
   </meta>
   <einkaufliste>
      <Rueebli-Haferflocken>
          <quant>90 g</quant>
          <zutat>grobe Haferflocken</zutat>
          <quant>1/2 TL</quant>
          <zutat>Backpulver</zutat>
          <quant>1/4 TL</quant>
          <zutat>Ingwer, gerieben</zutat>
          <quant>1/4 TL</quant>
          <zutat>Zimt</zutat>
          <quant>1/2 </quant>
          <zutat>Vanilleschote, laengs aufgeschnitten, Samen ausgekratzt</zutat>
          <quant>1 Prise</quant>
          <zutat>Fleur de Sel</zutat>
          <quant>1 EL</quant>
          <zutat>Rohzucker</zutat>
          <quant>1/2 </quant>
          <zutat>Bio-Zitrone, abgeriebene Schale</zutat>
          <quant>150 g</quant>
          <zutat>Rueebli, gerieben</zutat>
          <quant>30 g</quant>
          <zutat>saure getrocknete Aprikosen , fein gehackt</zutat>
          <quant>1 </quant>
          <zutat>Ei</zutat>
          <quant>2 dl</quant>
          <zutat>Milch</zutat>
      </Rueebli-Haferflocken>
      <Knusper-Topping>
          <quant>3 EL</quant>
          <zutat>Honig</zutat>
          <quant>30 g</quant>
          <zutat>Butter, fluessig</zutat>
          <quant>30 g</quant>
          <zutat>Sonnenblumenkerne</zutat>
          <quant>30 g</quant>
          <zutat>Kuerbiskerne</zutat>
          <quant>70 g</quant>
          <zutat>Baumnuesse, grob gehackt</zutat>
      </Knusper-Topping>
   </einkaufliste>
   <rezept>
      <Rueebli-Haferflocken>
          <inhalt>Alle Zutaten bis und mit Aprikosen in einer Schuessel mischen, in die vorbereitete Form geben. Ei und Milch verruehren, ueber die Haferflocken giessen. </inhalt>
      </Rueebli-Haferflocken>
      <Knusper-Topping>
          <inhalt>Honig und alle Zutaten bis und mit Baumnuessen in einer Schuessel mischen, bis die Masse etwas feucht ist. Gleichmaessig ueber die Haferflocken verteilen. </inhalt>
      </Knusper-Topping>
      <Backen    >
          <inhalt>Ca. 30 Min. in der Mitte des auf 180 Grad vorgeheizten Ofens. Auskuehlen lassen, mit einer Gabel lockern. </inhalt>
      </Backen    >
   </rezept>
</Rezept>