<?xml version="1.0" encoding="UTF-8"?>
<Rezept>
   <meta>
       <NaehrwertProPerson>355 kcal</NaehrwertProPerson>
       <Fett>19 g  </Fett>
       <Kohlenhydrate>6 g   </Kohlenhydrate>
       <Eiweiss>33 g  </Eiweiss>
   </meta>
   <einkaufliste>
      <Pilze_&amp;_Gemuese>
          <quant>1 EL</quant>
          <zutat>Olivenoel</zutat>
          <quant>1 </quant>
          <zutat>Schalotte, fein gehackt</zutat>
          <quant>250 g</quant>
          <zutat>gemischte  Pilze (z.B. Champignons,  Eierschwaemme), je nach Groesse halbiert oder geviertelt</zutat>
          <quant>15 </quant>
          <zutat>Cherry-Tomaten, geviertelt</zutat>
          <quant>1 </quant>
          <zutat>rote Peperoni, in Streifen</zutat>
          <quant>1 dl</quant>
          <zutat>Weisswein</zutat>
          <quant>1 Bund</quant>
          <zutat>glattblaettrige Petersilie, fein geschnitten</zutat>
          <quant>1 Zweiglein</quant>
          <zutat>Rosmarin, Nadeln abgezupft</zutat>
          <quant>10 </quant>
          <zutat>schwarze Oliven</zutat>
          <quant> </quant>
          <zutat>Salz, Pfeffer, nach Bedarf</zutat>
      </Pilze_&amp;_Gemuese>
      <Fisch     >
          <quant>4 </quant>
          <zutat>Forellenfilets (Bio) oder Seeforellenfilets (mit Haut)</zutat>
          <quant>3 Zweiglein</quant>
          <zutat>Thymian, fein geschnitten</zutat>
          <quant>1 Prise</quant>
          <zutat>Curry</zutat>
          <quant> </quant>
          <zutat>Salz, Pfeffer, nach Bedarf</zutat>
          <quant>4 Blaetter</quant>
          <zutat>Backpapiere</zutat>
          <quant>10 g</quant>
          <zutat>Butter</zutat>
          <quant>1 </quant>
          <zutat>Eiweiss, verklopft</zutat>
      </Fisch     >
   </einkaufliste>
   <rezept>
      <How_To    >
          <inhalt>Pilze &amp; Gemuese            </inhalt>
      </How_To    >
      <Pilze_&amp;_Gemuese>
          <inhalt>Fisch                         </inhalt>
      </Pilze_&amp;_Gemuese>
      <Fisch     >
          <inhalt>Backen: 20-25 Min. in der Mitte des auf 180 Grad vorgeheizten Ofens. Paeckchen aufschneiden, den Inhalt - Fisch, Gemuese und Garfond - auf Tellern anrichten.</inhalt>
      </Fisch     >
   </rezept>
</Rezept>