<?xml version="1.0" encoding="UTF-8"?>
<Rezept>
   <meta>
       <NaehrwertProPerson>190 kcal</NaehrwertProPerson>
       <Fett>10 g  </Fett>
       <Kohlenhydrate>18 g  </Kohlenhydrate>
       <Eiweiss>5 g   </Eiweiss>
   </meta>
   <einkaufliste>
      <Bulgur_kochen>
          <quant>1 1/2 dl</quant>
          <zutat>Wasser</zutat>
          <quant>50 g</quant>
          <zutat>Bulgur</zutat>
          <quant>1/2 TL</quant>
          <zutat>Fleur de Sel</zutat>
      </Bulgur_kochen>
      <Salat     >
          <quant>2 </quant>
          <zutat>Bundzwiebeln mit dem Gruen, in feinen Ringen</zutat>
          <quant>2 </quant>
          <zutat>Tomaten, in Wuerfeli</zutat>
          <quant>1 </quant>
          <zutat>Nostrano-Gurke, entkernt, in Wuerfeli</zutat>
          <quant>1 Bund</quant>
          <zutat>glattblaettrige Petersilie, fein geschnitten</zutat>
          <quant>1 Bund</quant>
          <zutat>Pfefferminze, fein geschnitten</zutat>
          <quant>1 </quant>
          <zutat>roter Chili, entkernt, fein gehackt</zutat>
          <quant>1 </quant>
          <zutat>Bio-Zitrone, abgeriebene Schale und Saft</zutat>
          <quant>3 EL</quant>
          <zutat>Olivenoel</zutat>
      </Salat     >
   </einkaufliste>
   <rezept>
      <Bulgur_kochen>
          <inhalt>Wasser mit dem Bulgur aufkochen, salzen, Hitze reduzieren, ca. 5 Min. koecheln. Pfanne von der Platte nehmen, ca. 5 Min. stehen lassen, abtropfen, etwas abkuehlen.</inhalt>
      </Bulgur_kochen>
      <Salat     >
          <inhalt>Zwiebeln und alle restlichen Zutaten  mischen. Bulgur daruntermischen, zugedeckt ca. 30 Min. ziehen lassen.</inhalt>
      </Salat     >
   </rezept>
</Rezept>