<?xml version="1.0" encoding="UTF-8"?>
<Rezept>
   <meta>
       <NaehrwertProPerson>1035 kcal</NaehrwertProPerson>
       <Fett>55 g  </Fett>
       <Kohlenhydrate>92 g  </Kohlenhydrate>
       <Eiweiss>40 g  </Eiweiss>
   </meta>
   <einkaufliste>
      <Nuesse_&amp;_Aroniabeeren>
          <quant>70 g</quant>
          <zutat>Baumnuesse, grob gehackt</zutat>
          <quant>10 g</quant>
          <zutat>getrocknete Aroniabeeren</zutat>
          <quant>1 EL</quant>
          <zutat>Ahornsirup (oder Yacon-Sirup)</zutat>
      </Nuesse_&amp;_Aroniabeeren>
      <Spaghetti >
          <quant>500 g</quant>
          <zutat>Spaghetti (Vollkorn)</zutat>
          <quant> </quant>
          <zutat>Salzwasser, siedend</zutat>
      </Spaghetti >
      <Speck_&amp;_Federkohl>
          <quant>250 g</quant>
          <zutat>geraeucherter Kochspeck, in feinen Streifen</zutat>
          <quant>600 g</quant>
          <zutat>Federkohl</zutat>
          <quant>3 dl</quant>
          <zutat>Halbrahm</zutat>
          <quant>1 TL</quant>
          <zutat>Gemuesebouillonpulver</zutat>
      </Speck_&amp;_Federkohl>
   </einkaufliste>
   <rezept>
      <Nuesse_&amp;_Aroniabeeren>
          <inhalt>Nuesse, Aroniabeeren und Sirup gut vermischen. In einer beschichteten Bratpfanne einige Minuten karamelisieren, Pfanne von der Herdplatte nehmen, auskuehlen.</inhalt>
      </Nuesse_&amp;_Aroniabeeren>
      <Spaghetti >
          <inhalt>Spaghetti im Salzwasser nach Verpackungsangabe al dente kochen, abtropfen, warmstellen.</inhalt>
      </Spaghetti >
      <Speck_&amp;_Federkohl>
          <inhalt>Speck ohne Zugabe von Fett in einer beschichteten Bratpfanne knusprig braten. Federkohl mit einer Schere vom Stiel entfernen, waschen. Noch tropfnass zum Speck geben und solange daempfen, bis er zusammenfaellt. Rahm und Bouillon beigeben, aufkochen. Federkohl unter die Spaghetti mischen, auf Tellern verteilen, Nuesse und Aroniabeeren darauf verteilen.</inhalt>
      </Speck_&amp;_Federkohl>
   </rezept>
</Rezept>