<?xml version="1.0" encoding="UTF-8"?>
<Rezept>
   <meta>
       <NaehrwertProPerson>76 kcal </NaehrwertProPerson>
       <Fett>2 g   </Fett>
       <Kohlenhydrate>12 g  </Kohlenhydrate>
       <Eiweiss>3 g   </Eiweiss>
   </meta>
   <einkaufliste>
      <Teig      >
          <quant>230 g</quant>
          <zutat>Weissmehl</zutat>
          <quant>215 g</quant>
          <zutat>Vollkornmehl</zutat>
          <quant>1/4 TL</quant>
          <zutat>Salz</zutat>
          <quant>2 1/2 dl</quant>
          <zutat>lauwarmes Wasser</zutat>
      </Teig      >
      <Fuellung   >
          <quant>250 g</quant>
          <zutat>Kuerbis (z.B. Butternuss), in Wuerfeln</zutat>
          <quant>wenig </quant>
          <zutat>Salzwasser, siedend</zutat>
          <quant>55 g</quant>
          <zutat>Cashew-Nuesse, ueber nacht in Wasser eingeweicht, abgetropft</zutat>
          <quant>4 EL</quant>
          <zutat>Edelhefe</zutat>
          <quant>3 </quant>
          <zutat>Knoblauchzehen</zutat>
          <quant>1 EL</quant>
          <zutat>Zitronensaft</zutat>
          <quant>1/2 dl</quant>
          <zutat>Gemuesebouillon</zutat>
          <quant>3 </quant>
          <zutat>Salbeiblaetter</zutat>
          <quant>1 TL</quant>
          <zutat>getrockneter Thymian</zutat>
          <quant>1/4 TL</quant>
          <zutat>Zimt</zutat>
          <quant>1/4 TL</quant>
          <zutat>Muskat</zutat>
          <quant>1/2 TL</quant>
          <zutat>Meersalz</zutat>
          <quant>wenig </quant>
          <zutat>Pfeffer</zutat>
      </Fuellung   >
      <Ravioli_formen_&amp;_kochen>
          <quant> </quant>
          <zutat>Salzwasser, siedend</zutat>
      </Ravioli_formen_&amp;_kochen>
      <Sauce     >
          <quant>2 EL</quant>
          <zutat>Margarine</zutat>
          <quant>2 </quant>
          <zutat>Zwiebeln, gehackt</zutat>
          <quant>10 </quant>
          <zutat>Salbeiblaetter, fein geschnitten</zutat>
          <quant>1 1/2 dl</quant>
          <zutat>Weisswein</zutat>
          <quant> </quant>
          <zutat>Salz, Pfeffer, nach Bedarf</zutat>
      </Sauce     >
   </einkaufliste>
   <rezept>
      <Teig      >
          <inhalt>Mehl und Salz in einer Schuessel mischen. In der Mitte eine Mulde bilden, Wasser hineingiessen, zu einem festen, elastischen Teig verarbeiten, auf etwas Mehl ca. 5 Min. kneten. Teig zu einer Kugel formen, zurueck in die Schuessel geben, bis zur Verwendung zugedeckt ruhen lassen.</inhalt>
      </Teig      >
      <Fuellung   >
          <inhalt>Kuerbis im Salzwasser ca. 20 Min. kochen, bis er weich ist, sehr gut abtropfen. Kuerbis mit allen Zutaten bis und mit Pfeffer im Mixglas puerieren. Fuellung bis zur Verwendung zugedeckt kuehl stellen.</inhalt>
      </Fuellung   >
      <Ravioli_formen_&amp;_kochen>
          <inhalt>Teig auf wenig Mehl ca. 2 mm duenn auswallen. Ca. 60 Rondellen von je 10 cm Durchmesser ausstechen, auf ein mit wenig Mehl bestreutes Backpapier legen. Die Fuellung in die Mitte der Haelfte der Rondellen geben. Teigraender mit etwas Wasser bestreichen, gefuellte Rondellen mit den ungefuellten Rondellen bedecken, Teigraender gut andruecken.  Ravioli portionenweise im Salzwasser je ca. 3 Min. kochen, mit der Schaumkelle herausheben, gut abtropfen.</inhalt>
      </Ravioli_formen_&amp;_kochen>
      <Sauce     >
          <inhalt>Margarine in einer weiten Bratpfanne erhitzen, Zwiebeln ca. 3 Min. andaempfen. Salbei beigeben, 1 Min. mitdaempfen, Weisswein dazugiessen, wuerzen, aufkochen. Ravioli in die Sauce geben, ca. 1 Min. erhitzen, sofort anrichten.</inhalt>
      </Sauce     >
   </rezept>
</Rezept>