<?xml version="1.0" encoding="UTF-8"?>
<Rezept>
   <meta>
       <NaehrwertProPerson>513 kcal</NaehrwertProPerson>
       <Fett>40 g  </Fett>
       <Kohlenhydrate>25 g  </Kohlenhydrate>
       <Eiweiss>11 g  </Eiweiss>
   </meta>
   <einkaufliste>
      <Chili-Safran-Oel>
          <quant>1/2 dl</quant>
          <zutat>Olivenoel</zutat>
          <quant>1/4 TL</quant>
          <zutat>geraeucherter Paprika </zutat>
          <quant>1/4 TL</quant>
          <zutat>Chiliflocken, grob zerstossen</zutat>
          <quant>1 Msp.</quant>
          <zutat>Safran</zutat>
      </Chili-Safran-Oel>
      <Oliven-Kraeuter-Salat_>
          <quant>1/2 EL</quant>
          <zutat>Zitronensaft</zutat>
          <quant>2 EL</quant>
          <zutat>Olivenoel</zutat>
          <quant>1/2 TL</quant>
          <zutat>Kreuzkuemmel, grob zerstossen</zutat>
          <quant> </quant>
          <zutat>Salz, nach Bedarf</zutat>
          <quant>160 g</quant>
          <zutat>Kalamata-Oliven, abgetropft</zutat>
          <quant>4 EL</quant>
          <zutat>glattblaettrige Petersilie, zerzupft</zutat>
          <quant>2 EL</quant>
          <zutat>Pfefferminze, zerzupft</zutat>
      </Oliven-Kraeuter-Salat_>
      <Eier      >
          <quant>2 EL</quant>
          <zutat>Olivenoel</zutat>
          <quant>4 </quant>
          <zutat>frische Eier</zutat>
          <quant>1/4 TL</quant>
          <zutat>Kreuzkuemmel, grob zerstossen</zutat>
          <quant> </quant>
          <zutat>Salz, Pfeffer, nach Bedarf</zutat>
          <quant>200 g</quant>
          <zutat>Brot in Scheiben, geroestet</zutat>
      </Eier      >
   </einkaufliste>
   <rezept>
      <Chili-Safran-Oel>
          <inhalt>Oel und Gewuerze in einer Pfanne erwaermen, bei kleinster Hitze ca. 30 Min. ziehen lassen. </inhalt>
      </Chili-Safran-Oel>
      <Oliven-Kraeuter-Salat_>
          <inhalt>Zitronensaft, Oel und Kreuzkuemmel verruehren, salzen. Oliven und Kraeuter beigeben, mischen. </inhalt>
      </Oliven-Kraeuter-Salat_>
      <Eier      >
          <inhalt>Oel in einer Bratpfanne erhitzen. Eier einzeln aufschlagen, in die Pfanne gleiten lassen, ca. 2 Min. anbraten. Hitze reduzieren, ca. 3 Min. fertig braten, wuerzen. Chili-Safran-Oel daruebertraeufeln, mit Brot und Oliven-Kraeuter-Salat servieren. </inhalt>
      </Eier      >
   </rezept>
</Rezept>