<?xml version="1.0" encoding="UTF-8"?>
<Rezept>
   <meta>
       <NaehrwertProPerson>440 kcal</NaehrwertProPerson>
       <Fett>19 g  </Fett>
       <Kohlenhydrate>39 g  </Kohlenhydrate>
       <Eiweiss>24 g  </Eiweiss>
   </meta>
   <einkaufliste>
      <Kartoffeln>
          <quant>400 g</quant>
          <zutat>Baby-Kartoffeln, laengs halbiert</zutat>
          <quant>100 g</quant>
          <zutat>schwarze Linsen (Beluga)</zutat>
          <quant> </quant>
          <zutat>Salzwasser, siedend</zutat>
      </Kartoffeln>
      <Gemuese_   >
          <quant>30 g</quant>
          <zutat>Mandeln, grob gehackt</zutat>
          <quant> </quant>
          <zutat>Oel zum Braten</zutat>
          <quant>500 g</quant>
          <zutat>gruene Spargeln, schraeg in ca. 1 cm dicken Scheiben</zutat>
          <quant>250 g</quant>
          <zutat>Kefen, schraeg gedrittelt</zutat>
          <quant>250 g</quant>
          <zutat>tiefgekuehlte geschaelte gekochte Crevetten (Bio), aufgetaut</zutat>
          <quant>1 TL</quant>
          <zutat>Salz</zutat>
      </Gemuese_   >
      <Dressing  >
          <quant>4 EL</quant>
          <zutat>Zitronensaft</zutat>
          <quant>4 EL</quant>
          <zutat>Olivenoel</zutat>
          <quant>1/2 dl</quant>
          <zutat>Gemuesebouillon</zutat>
          <quant>1/4 TL</quant>
          <zutat>Salz</zutat>
          <quant>wenig </quant>
          <zutat>Pfeffer</zutat>
          <quant>1 Bund</quant>
          <zutat>Baerlauch, fein geschnitten</zutat>
      </Dressing  >
   </einkaufliste>
   <rezept>
      <Kartoffeln>
          <inhalt>Kartoffeln und Linsen in Salzwasser ca. 20 Min. kochen, abtropfen. </inhalt>
      </Kartoffeln>
      <Gemuese_   >
          <inhalt>Mandeln ohne Fett in einer Bratpfanne goldbraun roesten, herausnehmen, beiseite stellen. Oel in derselben Pfanne erhitzen, Kartoffeln und Linsen ca. 5 Min. braten, in eine Schuessel geben. Wenig Oel beigeben Spargeln und Kefen ca. 5 Min. anbraten, Crevetten beigeben, ca. 2 Min. mitbraten, salzen, zu den Kartoffeln geben, mischen. </inhalt>
      </Gemuese_   >
      <Dressing  >
          <inhalt>Zitronensaft, Oel und Bouillon verruehren, wuerzen. Baerlauch, Gemuese und Crevetten beigeben, mischen. Beiseite gestellte Mandeln darueberstreuen. </inhalt>
      </Dressing  >
   </rezept>
</Rezept>