<?xml version="1.0" encoding="UTF-8"?>
<Rezept>
   <meta>
       <NaehrwertProPerson>886 kcal</NaehrwertProPerson>
       <Fett>76 g  </Fett>
       <Kohlenhydrate>33 g  </Kohlenhydrate>
       <Eiweiss>14 g  </Eiweiss>
   </meta>
   <einkaufliste>
      <Faecherkartoffeln>
          <quant>800 g</quant>
          <zutat>Kartoffeln</zutat>
          <quant>1/2 TL</quant>
          <zutat>Salz</zutat>
          <quant>wenig </quant>
          <zutat>Pfeffer</zutat>
          <quant>50 g</quant>
          <zutat>Butter, in kleinen Stuecken</zutat>
      </Faecherkartoffeln>
      <Backen    >
          <quant>250 g</quant>
          <zutat>Rueebli, laengs gesechstelt</zutat>
          <quant>1 TL</quant>
          <zutat>Zucker</zutat>
          <quant>1 EL</quant>
          <zutat>Butter</zutat>
          <quant>1/4 TL</quant>
          <zutat>Salz</zutat>
      </Backen    >
      <Pesto_    >
          <quant>100 g</quant>
          <zutat>Mandeln</zutat>
          <quant>180 g</quant>
          <zutat>Basilikum-Pesto</zutat>
          <quant>90 g</quant>
          <zutat>gruene Oliven, grob geschnitten</zutat>
          <quant>100 g</quant>
          <zutat>Creme fraiche</zutat>
      </Pesto_    >
   </einkaufliste>
   <rezept>
      <Faecherkartoffeln>
          <inhalt>Kartoffeln auf einen Essloeffel legen und sorgfaeltig faecherartig einschneiden. Kartoffeln auf ein mit Backpapier belegtes Blech legen, wuerzen. Butter darauf verteilen.  </inhalt>
      </Faecherkartoffeln>
      <Backen    >
          <inhalt>Ca. 30 Min. in der unteren Haelfte des auf 220 Grad vorgeheizten Ofens. Rueebli, Zucker und Butter mischen, salzen, zu den Kartoffeln geben, ca. 20 Min. fertig backen. </inhalt>
      </Backen    >
      <Pesto_    >
          <inhalt>Mandeln in einer Bratpfanne ohne Fett goldbraun roesten, grob hacken. Pesto, Oliven und Mandeln mischen. Auf den Kartoffeln und Rueebli verteilen. Creme fraiche darauf verteilen. </inhalt>
      </Pesto_    >
   </rezept>
</Rezept>