<?xml version="1.0" encoding="UTF-8"?>
<Rezept>
   <meta>
       <NaehrwertProPerson>293 kcal</NaehrwertProPerson>
       <Fett>17 g  </Fett>
       <Kohlenhydrate>8 g   </Kohlenhydrate>
       <Eiweiss>27 g  </Eiweiss>
   </meta>
   <einkaufliste>
      <Marinade  >
          <quant>1 cm</quant>
          <zutat>Ingwer, fein gehackt</zutat>
          <quant>1 </quant>
          <zutat>Knoblauchzehe, gepresst</zutat>
          <quant>1 </quant>
          <zutat>roter Chili, entkernt, fein gehackt</zutat>
          <quant>1 </quant>
          <zutat>Bundzwiebel mit dem Gruen, fein gehackt</zutat>
          <quant>1/4 Bund</quant>
          <zutat>glattblaettrige Petersilie, fein geschnitten</zutat>
          <quant>1/4 Bund</quant>
          <zutat>Koriander, fein geschnitten</zutat>
          <quant>1/4 TL</quant>
          <zutat>Pfeffer (schwarz)</zutat>
          <quant>1 EL</quant>
          <zutat>fluessiger Honig</zutat>
          <quant>1/2 EL</quant>
          <zutat>Rohzucker</zutat>
          <quant>1/2 </quant>
          <zutat>Limette, nur der Saft</zutat>
      </Marinade  >
      <Pouletschenkel>
          <quant>400 g</quant>
          <zutat>Poulet-Unterschenkel</zutat>
          <quant>400 g</quant>
          <zutat>Poulet-Oberschenkel</zutat>
      </Pouletschenkel>
      <Grillieren_(Holzkohle-/Gas-/Elektrogrill)>
          <quant>3/4 TL</quant>
          <zutat>Salz</zutat>
          <quant>1 </quant>
          <zutat>Limette, nur Saft</zutat>
      </Grillieren_(Holzkohle-/Gas-/Elektrogrill)>
   </einkaufliste>
   <rezept>
      <How_To    >
          <inhalt>Marinade                      </inhalt>
      </How_To    >
      <Marinade  >
          <inhalt>Pouletschenkel                </inhalt>
      </Marinade  >
      <Pouletschenkel>
          <inhalt>Grillieren (Holzkohle-/Gas-/Elektrogrill)</inhalt>
      </Pouletschenkel>
      <Grillieren_(Holzkohle-/Gas-/Elektrogrill)>
          <inhalt>Poulet ueber mittelstarker Glut/ auf mittlerer Stufe (ca. 200 Grad C) unter gelegentlichem Wenden ca. 30 Min. grillieren, von Zeit zu Zeit mit Limettensaft betraeufeln.</inhalt>
      </Grillieren_(Holzkohle-/Gas-/Elektrogrill)>
   </rezept>
</Rezept>