<?xml version="1.0" encoding="UTF-8"?>
<Rezept>
   <meta>
       <NaehrwertProPerson>358 kcal</NaehrwertProPerson>
       <Fett>22 g  </Fett>
       <Kohlenhydrate>33 g  </Kohlenhydrate>
       <Eiweiss>12 g  </Eiweiss>
   </meta>
   <einkaufliste>
      <Streusel  >
          <quant>40 g</quant>
          <zutat>Zwieback, grob zerbroeckelt</zutat>
          <quant>3 EL</quant>
          <zutat>gemahlene geschaelte Mandeln</zutat>
          <quant>2 EL</quant>
          <zutat>Zucker</zutat>
          <quant>1 TL</quant>
          <zutat>Lebkuchengewuerz</zutat>
      </Streusel  >
      <Himbeeren >
          <quant>250 g</quant>
          <zutat>tiefgekuehlte Himbeeren, aufgetaut</zutat>
          <quant>2 EL</quant>
          <zutat>Ahornsirup</zutat>
          <quant>1/2 TL</quant>
          <zutat>Lebkuchengewuerz</zutat>
      </Himbeeren >
      <Quarkcreme>
          <quant>250 g</quant>
          <zutat>Magerquark</zutat>
          <quant>3 EL</quant>
          <zutat>Ahornsirup</zutat>
          <quant>2 dl</quant>
          <zutat>Vollrahm, steif geschlagen</zutat>
      </Quarkcreme>
   </einkaufliste>
   <rezept>
      <Streusel  >
          <inhalt>Zwieback mit Mandeln, Zucker und Lebkuchengewuerz in einer Bratpfanne bei mittlerer Hitze unter gelegentlichem Ruehren ca. 5 Min. roesten. Streusel auskuehlen. </inhalt>
      </Streusel  >
      <Himbeeren >
          <inhalt>Himbeeren, Ahornsirup und Lebkuchengewuerz mischen.</inhalt>
      </Himbeeren >
      <Quarkcreme>
          <inhalt>Quark und Ahornsirup verruehren, Schlagrahm darunterziehen. Creme abwechselnd mit den Himbeeren in Schaelchen fuellen, Streusel darueberstreuen.</inhalt>
      </Quarkcreme>
   </rezept>
</Rezept>