<?xml version="1.0" encoding="UTF-8"?>
<Rezept>
   <meta>
       <NaehrwertProPerson>266 kcal</NaehrwertProPerson>
       <Fett>15 g  </Fett>
       <Kohlenhydrate>27 g  </Kohlenhydrate>
       <Eiweiss>5 g   </Eiweiss>
   </meta>
   <einkaufliste>
      <Teig      >
          <quant>200 g</quant>
          <zutat>Butter, weich</zutat>
          <quant>150 g</quant>
          <zutat>Zucker</zutat>
          <quant>1/4 TL</quant>
          <zutat>Salz</zutat>
          <quant>1 TL</quant>
          <zutat>Vanillepaste</zutat>
          <quant>4 </quant>
          <zutat>Eier</zutat>
          <quant>200 g</quant>
          <zutat>Weissmehl</zutat>
          <quant>100 g</quant>
          <zutat>gemahlene geschaelte Mandeln</zutat>
          <quant>1 TL</quant>
          <zutat>Backpulver</zutat>
          <quant>2 Zweiglein</quant>
          <zutat>Rosmarin, fein geschnitten</zutat>
          <quant>1 </quant>
          <zutat>Pomelo, geschaelt, Haeutchen entfernt, Fruchfleisch fein zerzupft, 1 EL beiseite stellen</zutat>
      </Teig      >
      <Traenken   >
          <quant>1 </quant>
          <zutat>Pomelo, nur Saft (ergibt ca. 1 dl)</zutat>
          <quant>2 </quant>
          <zutat>Limetten, nur Saft (ergibt ca. 1/2 dl)</zutat>
          <quant>1/2 dl</quant>
          <zutat>Wasser</zutat>
          <quant>40 g</quant>
          <zutat>Puderzucker</zutat>
      </Traenken   >
      <Kandierter_Rosmarin>
          <quant>1 EL</quant>
          <zutat>Wasser</zutat>
          <quant>1 EL</quant>
          <zutat>Zucker</zutat>
          <quant>2 Zweiglein</quant>
          <zutat>Rosmarin, Nadeln abgezupft</zutat>
          <quant>4 EL</quant>
          <zutat>Puderzucker</zutat>
      </Kandierter_Rosmarin>
   </einkaufliste>
   <rezept>
      <Teig      >
          <inhalt>Butter in eine Schuessel geben, Zucker, Salz und Vanillepaste mit den Schwingbesen des Handruehrgeraets darunterruehren. Ein Ei nach dem anderen darunterruehren, weiterruehren, bis die Masse heller ist. Mehl, Mandeln, Backpulver, Rosmarin und Pomeloschale mischen, mit dem Pomelo-Fruchtfleisch daruntermischen. Teig in die vorbereitete Form fuellen. </inhalt>
      </Teig      >
      <Backen    >
          <inhalt>Ca. 1 Std. in der unteren Haelfte des auf 180 Grad vorgeheizten Ofens. Cake herausnehmen, etwas abkuehlen, mit einem Holzspiesschen dicht einstechen. </inhalt>
      </Backen    >
      <Traenken   >
          <inhalt>Pomelo- und Limettensaft mit dem Wasser und Puderzucker verruehren, 1 EL beiseite stellen. Guss ueber den Cake giessen, ca. 10 Min. stehen lassen. Cake aus der Form nehmen, auf deinem Gitter auskuehlen. </inhalt>
      </Traenken   >
      <Kandierter_Rosmarin>
          <inhalt>Wasser mit dem Zucker in einer kleinen Pfanne aufkochen, sirupartig einkoecheln. Rosmarin beigeben, unter staendigem Ruehren bei mittlerer Hitze einkochen, bis der Zucker trocken wird und an den Nadeln haftet. Pfanne von der Platte nehmen ca. 2 Min. weiterruehren. Rosmarin auf einem Backpapier auskuehlen. Beiseite gestellten Guss mit Puderzucker verruehren, ueber den Kuchen traeufeln. Mit dem beiseite gestellten Pomelo-Fruchtfleisch und Rosmarin garnieren.</inhalt>
      </Kandierter_Rosmarin>
   </rezept>
</Rezept>