<?xml version="1.0" encoding="UTF-8"?>
<Rezept>
   <meta>
       <NaehrwertProPerson>694 kcal</NaehrwertProPerson>
       <Fett>25 g  </Fett>
       <Kohlenhydrate>90 g  </Kohlenhydrate>
       <Eiweiss>23 g  </Eiweiss>
   </meta>
   <einkaufliste>
      <Knusper-Broesmeli>
          <quant>2 EL</quant>
          <zutat>Olivenoel</zutat>
          <quant>6 EL</quant>
          <zutat>Panko oder Paniermehl</zutat>
          <quant>2 </quant>
          <zutat>Knoblauchzehen, gepresst</zutat>
          <quant>1/2 Bund</quant>
          <zutat>Basilikum, fein geschnitten</zutat>
          <quant>1/2 Bund</quant>
          <zutat>Pfefferminze, fein geschnitten</zutat>
          <quant>2 EL</quant>
          <zutat>Pinienkerne</zutat>
          <quant>1/4 TL</quant>
          <zutat>Fleur de Sel</zutat>
      </Knusper-Broesmeli>
      <Spargeln  >
          <quant>2 EL</quant>
          <zutat>Olivenoel</zutat>
          <quant>3 </quant>
          <zutat>Bundzwiebeln mit dem Gruen, laengs geviertelt, in ca. 5 cm langen Stuecken,</zutat>
          <quant>500 g</quant>
          <zutat>gruene Spargeln unteres Drittel geschaelt, Spargel laengs geviertelt, in ca. 5 cm grossen Stuecken</zutat>
          <quant>1/2 TL</quant>
          <zutat>Salz</zutat>
          <quant>wenig </quant>
          <zutat>Pfeffer</zutat>
      </Spargeln  >
      <Pasta     >
          <quant>400 g</quant>
          <zutat>Orecchiette </zutat>
          <quant> </quant>
          <zutat>Salzwasser, siedend</zutat>
          <quant>1 </quant>
          <zutat>Burrata (ca. 150 g)</zutat>
          <quant>1/2 Bund</quant>
          <zutat>Basilikum, zerzupft</zutat>
      </Pasta     >
   </einkaufliste>
   <rezept>
      <Knusper-Broesmeli>
          <inhalt>Oel in einer beschichteten Bratpfanne erhitzen. Panko, Knoblauch, Kraeuter und Pinienkerne beigeben, ca. 5 Min. mitbraten. Herausnehmen, salzen, beiseite stellen. </inhalt>
      </Knusper-Broesmeli>
      <Spargeln  >
          <inhalt>Oel in derselben Pfanne erhitzen. Bundzwiebeln und Spargeln ca. 5 Min. ruehrbraten, wuerzen. </inhalt>
      </Spargeln  >
      <Pasta     >
          <inhalt>Orecchiette im siedenden Salzwasser knapp al dente kochen, ca. 1 dl Kochwasser beiseite stellen. Orecchiette abtropfen, mit dem beiseite gestellten Kochwasser zu den Spargeln geben, mischen. Burrata zerzupfen, mit dem Basilikum daruntermischen, Knusper-Broesmeli darueberstreuen. </inhalt>
      </Pasta     >
   </rezept>
</Rezept>