<?xml version="1.0" encoding="UTF-8"?>
<Rezept>
   <meta>
       <NaehrwertProPerson>942 kcal</NaehrwertProPerson>
       <Fett>46 g  </Fett>
       <Kohlenhydrate>76 g  </Kohlenhydrate>
       <Eiweiss>57 g  </Eiweiss>
   </meta>
   <einkaufliste>
      <Vorbereiten>
          <quant>wenig </quant>
          <zutat>Butter</zutat>
      </Vorbereiten>
      <Hoernli    >
          <quant>350 g</quant>
          <zutat>Teigwaren (z.B. Hoernli)</zutat>
          <quant> </quant>
          <zutat>Salzwasser, siedend</zutat>
      </Hoernli    >
      <Hackfleisch_>
          <quant>1 </quant>
          <zutat>Zwiebel</zutat>
          <quant>1 </quant>
          <zutat>Knoblauchzehe</zutat>
          <quant>1 EL</quant>
          <zutat>Oel</zutat>
          <quant>500 g</quant>
          <zutat>Hackfleisch (Rind)</zutat>
          <quant>1/2 TL</quant>
          <zutat>Salz</zutat>
          <quant>wenig </quant>
          <zutat>Pfeffer</zutat>
          <quant>3 EL</quant>
          <zutat>Tomatenpueree</zutat>
          <quant>4 dl</quant>
          <zutat>Gemuesebouillon</zutat>
      </Hackfleisch_>
      <Kaese_und_Aepfel>
          <quant>300 g</quant>
          <zutat>Raclettekaese</zutat>
          <quant>2 </quant>
          <zutat>rotschalige Aepfel</zutat>
          <quant>wenig </quant>
          <zutat>Butter</zutat>
          <quant>350 g</quant>
          <zutat>Teigwaren (z.B. Hoernli)</zutat>
          <quant> </quant>
          <zutat>Salzwasser, siedend</zutat>
          <quant>1 </quant>
          <zutat>Zwiebel</zutat>
          <quant>1 </quant>
          <zutat>Knoblauchzehe</zutat>
          <quant>1 EL</quant>
          <zutat>Oel</zutat>
          <quant>500 g</quant>
          <zutat>Hackfleisch (Rind)</zutat>
          <quant>1/2 TL</quant>
          <zutat>Salz</zutat>
          <quant>wenig </quant>
          <zutat>Pfeffer</zutat>
          <quant>3 EL</quant>
          <zutat>Tomatenpueree</zutat>
          <quant>4 dl</quant>
          <zutat>Gemuesebouillon</zutat>
          <quant>300 g</quant>
          <zutat>Raclettekaese</zutat>
          <quant>2 </quant>
          <zutat>rotschalige Aepfel</zutat>
      </Kaese_und_Aepfel>
   </einkaufliste>
   <rezept>
      <Vorbereiten>
          <inhalt>                              </inhalt>
      </Vorbereiten>
      <Hoernli    >
          <inhalt>Teigwaren im siedenden Salzwasser ca. 4 Min. kochen, abtropfen, in die vorbereitete Form geben. </inhalt>
      </Hoernli    >
      <Hackfleisch_>
          <inhalt>Zwiebel schaelen, fein hacken, Knoblauch pressen. Oel in einer Bratpfanne erhitzen. Fleisch portionenweise je ca. 5 Min. anbraten. Herausnehmen, wuerzen. Hitze reduzieren, </inhalt>
      </Hackfleisch_>
      <Kaese_und_Aepfel>
          <inhalt>Kaese an der Roestiraffel grob reiben. </inhalt>
      </Kaese_und_Aepfel>
      <Backen    >
          <inhalt>Ca. 30 Min. in der Mitte des auf 180 Grad vorgeheizten Ofens. </inhalt>
      </Backen    >
   </rezept>
</Rezept>