<?xml version="1.0" encoding="UTF-8"?>
<Rezept>
   <meta>
       <NaehrwertProPerson>104 kcal</NaehrwertProPerson>
       <Fett>4 g   </Fett>
       <Kohlenhydrate>16 g  </Kohlenhydrate>
       <Eiweiss>1 g   </Eiweiss>
   </meta>
   <einkaufliste>
      <Pingus    >
          <quant>4 </quant>
          <zutat>Bananen</zutat>
          <quant>1/2 Beutel</quant>
          <zutat>dunkle Kuchenglasur (ca. 60 g)</zutat>
          <quant>12 </quant>
          <zutat>Smarties</zutat>
          <quant>16 </quant>
          <zutat>Zucker-Augen</zutat>
          <quant>4 </quant>
          <zutat>Bananen</zutat>
          <quant>1/2 Beutel</quant>
          <zutat>dunkle Kuchenglasur (ca. 60 g)</zutat>
          <quant>12 </quant>
          <zutat>Smarties</zutat>
          <quant>16 </quant>
          <zutat>Zucker-Augen</zutat>
      </Pingus    >
   </einkaufliste>
   <rezept>
      <How_To    >
          <inhalt>Pingus                        </inhalt>
      </How_To    >
      <Pingus    >
          <inhalt>                              </inhalt>
      </Pingus    >
   </rezept>
</Rezept>