<?xml version="1.0" encoding="UTF-8"?>
<Rezept>
   <meta>
       <NaehrwertProPerson>278 kcal</NaehrwertProPerson>
       <Fett>17 g  </Fett>
       <Kohlenhydrate>22 g  </Kohlenhydrate>
       <Eiweiss>7 g   </Eiweiss>
   </meta>
   <einkaufliste>
      <Teig      >
          <quant>125 g</quant>
          <zutat>Dinkelvollkornmehl</zutat>
          <quant>75 g</quant>
          <zutat>helles Dinkelmehl</zutat>
          <quant>1/2 TL</quant>
          <zutat>Salz</zutat>
          <quant>75 g</quant>
          <zutat>Butter, in Stuecken, kalt</zutat>
          <quant>3/4 dl</quant>
          <zutat>Wasser</zutat>
      </Teig      >
      <Tarte     >
          <quant>125 g</quant>
          <zutat>Frischkaese</zutat>
          <quant>300 g</quant>
          <zutat>Aprikosen, in Schnitzen</zutat>
          <quant>250 g</quant>
          <zutat>Pfirsiche, in Schnitzen</zutat>
          <quant>3 </quant>
          <zutat>Bundzwiebeln, in Ringen</zutat>
          <quant>150 g</quant>
          <zutat>Ziegenfrischkaese, zerbroeckelt</zutat>
          <quant>2 Prisen</quant>
          <zutat>Salz</zutat>
          <quant>wenig </quant>
          <zutat>Pfeffer</zutat>
      </Tarte     >
      <Backen    >
          <quant>2 EL</quant>
          <zutat>Olivenoel</zutat>
          <quant>1/2 Bund</quant>
          <zutat>Majoran, fein geschnitten</zutat>
          <quant>1/2 TL</quant>
          <zutat>Pfeffer</zutat>
      </Backen    >
   </einkaufliste>
   <rezept>
      <How_To    >
          <inhalt>Teig                          </inhalt>
      </How_To    >
      <Teig      >
          <inhalt>Teig auf wenig Mehl (ca. 32 cm Ø) auswallen, in das vorbereitete Blech legen. Teigboden mit einer Gabel dicht einstechen, ca. 15 Min. kuehl stellen.</inhalt>
      </Teig      >
      <Tarte     >
          <inhalt>Frischkaese auf dem Tarteboden verteilen.  Aprikosen, Pfirsiche, Bundzwiebeln und Ziegenkaese darauf verteilen, wuerzen. </inhalt>
      </Tarte     >
      <Backen    >
          <inhalt>Ca. 35 Min. auf der untersten Rille des auf 220 Grad vorgeheizten Ofens. Herausnehmen, etwas abkuehlen. Oel und Majoran verruehren, wuerzen, ueber die Tarte traeufeln, anrichten. </inhalt>
      </Backen    >
   </rezept>
</Rezept>