<?xml version="1.0" encoding="UTF-8"?>
<Rezept>
   <meta>
       <NaehrwertProPerson>583 kcal</NaehrwertProPerson>
       <Fett>20 g  </Fett>
       <Kohlenhydrate>47 g  </Kohlenhydrate>
       <Eiweiss>51 g  </Eiweiss>
   </meta>
   <einkaufliste>
      <Saltimbocca>
          <quant>6 </quant>
          <zutat>Forellenfilets (Bio) (je ca. 100 g)</zutat>
          <quant>1/4 TL</quant>
          <zutat>Salz</zutat>
          <quant>wenig </quant>
          <zutat>Pfeffer</zutat>
          <quant>12 </quant>
          <zutat>Salbeiblaetter</zutat>
          <quant>6 Tranchen</quant>
          <zutat>Rohschinken (ca. 80 g)</zutat>
          <quant>2 </quant>
          <zutat>Zucchetti, laengs in Scheiben</zutat>
          <quant>1 EL</quant>
          <zutat>Olivenoel</zutat>
      </Saltimbocca>
      <Risoni-Salat>
          <quant>2 TL</quant>
          <zutat>milder Senf</zutat>
          <quant>1 </quant>
          <zutat>Bio-Zitrone, heiss abgespuelt, trocken getupft, wenig abgeriebene Schale und ganzer Saft</zutat>
          <quant>3 EL</quant>
          <zutat>Olivenoel</zutat>
          <quant>1 TL</quant>
          <zutat>Salz</zutat>
          <quant>1/4 TL</quant>
          <zutat>Pfeffer</zutat>
          <quant>250 g</quant>
          <zutat>Teigwaren (z.B. Risoni)</zutat>
          <quant> </quant>
          <zutat>Salzwasser, siedend</zutat>
          <quant>200 g</quant>
          <zutat>Jungspinat</zutat>
      </Risoni-Salat>
   </einkaufliste>
   <rezept>
      <Saltimbocca>
          <inhalt>Fischfilets quer halbieren, wuerzen. Auf die Haelfte der Fischstuecke je zwei Salbeiblaetter legen, restliche Fischstuecke darauflegen, mit Rohschninken umwickeln. Zucchettischeiben mit Oel bestreichen.</inhalt>
      </Saltimbocca>
      <Risoni-Salat>
          <inhalt>Senf und alle Zutaten bis und mit Pfeffer in einer Schuessel verruehren. Teigwaren im Salzwasser al dente kochen, abtropfen, mit dem Spinat zur Sauce geben, mischen. </inhalt>
      </Risoni-Salat>
      <Grillieren_(Holzkohle-,_Gas-,_Elektrogrill)>
          <inhalt>Saltimbocca und Zucchetti bei geschlossenem Deckel ueber mittelstarker Glut / auf mittlerer Stufe (ca. 200 Grad) beidseitig je ca. 4 Min. grillieren. Zucchetti in Stuecke schneiden, unter den Risoni-Salat mischen. Saltimbocca mit dem Risoni-Salat anrichten. </inhalt>
      </Grillieren_(Holzkohle-,_Gas-,_Elektrogrill)>
   </rezept>
</Rezept>