<?xml version="1.0" encoding="UTF-8"?>
<Rezept>
   <meta>
       <NaehrwertProPerson>375 kcal</NaehrwertProPerson>
       <Fett>22 g  </Fett>
       <Kohlenhydrate>11 g  </Kohlenhydrate>
       <Eiweiss>30 g  </Eiweiss>
   </meta>
   <einkaufliste>
      <Fleisch   >
          <quant>500 g</quant>
          <zutat>Rindshuft, am Stueck</zutat>
          <quant>1 EL</quant>
          <zutat>Erdnussoel</zutat>
          <quant>1 TL</quant>
          <zutat>Salz</zutat>
          <quant>wenig </quant>
          <zutat>Pfeffer</zutat>
      </Fleisch   >
      <Gemuese    >
          <quant>2 </quant>
          <zutat>Zwiebeln</zutat>
          <quant>2 </quant>
          <zutat>rote Peperoni</zutat>
          <quant>250 g</quant>
          <zutat>Champignons</zutat>
          <quant>1 1/2 TL</quant>
          <zutat>Paprika edelsuess</zutat>
          <quant>1 EL</quant>
          <zutat>Erdnussoel</zutat>
          <quant>2 dl</quant>
          <zutat>Fleischbouillon</zutat>
      </Gemuese    >
      <Sauce     >
          <quant>1 1/2 TL</quant>
          <zutat>Maizena</zutat>
          <quant>1 dl</quant>
          <zutat>Vollrahm</zutat>
          <quant>100 g</quant>
          <zutat>Essiggurken</zutat>
      </Sauce     >
   </einkaufliste>
   <rezept>
      <Fleisch   >
          <inhalt>Fleisch in ca. 1 1/2 cm grosse Wuerfel schneiden, in einer Bratpfanne im heissen Oel rundum ca. 2 Min. anbraten, herausnehmen, wuerzen.</inhalt>
      </Fleisch   >
      <Gemuese    >
          <inhalt>Zwiebeln fein hacken, Peperoni in Streifen, Champignons in Scheiben schneiden. Oel in derselben Pfanne erwaermen, Gemuese und Paprika ca. 5 Min. andaempfen. Bouillon dazugiessen, aufkochen.</inhalt>
      </Gemuese    >
      <Sauce     >
          <inhalt>Maizena mit dem Rahm anruehren, dazugiessen, bei mittlerer Hitze ca. 5 Min. koecheln. Essiggurken in feine Streifen schneiden, mit dem Fleisch beigeben, nur noch heiss werden lassen.</inhalt>
      </Sauce     >
   </rezept>
   <video href="https://www.youtube.com/watch?v=I7e3o-6Vo58"/>
   <video href="https://www.youtube.com/watch?v=gd2vtJZ1xTw"/>
</Rezept>