{
    "info": {
        "CPU": [],
        "GPU": [],
        "MEM": [
            "09.11.2020 16:07 - MEM-Inf: 83.3% used"
        ],
        "DPC": [],
        "DMX": [],
        "DFR": []
    },
    "warn": {
        "CPU": [],
        "GPU": [],
        "MEM": [
            "09.11.2020 16:03 - MEM-Inf: 82.3% used",
            "09.11.2020 16:06 - MEM-Inf: 82.76666666666667% used"
        ],
        "DPC": [],
        "DMX": [],
        "DFR": []
    },
    "crit": {
        "CPU": [],
        "GPU": [],
        "MEM": [
            "06.11.2020 16:00 - MEM-Inf: 55.86666666666667% used",
            "06.11.2020 16:01 - MEM-Inf: 80.86666666666666% used"
        ],
        "DPC": [],
        "DMX": [],
        "DFR": []
    }
}